[
{
"id": "0",
"img": "https://raw.githubusercontent.com/thzzyt/senxi-conteudost/main/huds/2%20DEDOS/HUD%201.jpg",
"type": "2 DEDOS"
},
{
"id": "1",
"img": "https://raw.githubusercontent.com/thzzyt/senxi-conteudost/main/huds/2%20DEDOS/HUD%202.jpg",
"type": "2 DEDOS"
},
{
"id": "2",
"img": "https://raw.githubusercontent.com/thzzyt/senxi-conteudost/main/huds/2%20DEDOS/HUD%203.jpg",
"type": "2 DEDOS"
},
{
"id": "7",
"img": "https://raw.githubusercontent.com/thzzyt/senxi-conteudost/main/huds/3%20DEDOS/HUD%201.jpg",
"type": "3 DEDOS"
},
{
"id": "8",
"img": "https://raw.githubusercontent.com/thzzyt/senxi-conteudost/main/huds/3%20DEDOS/HUD%202.jpg",
"type": "3 DEDOS"
},
{
"id": "9",
"img": "https://raw.githubusercontent.com/thzzyt/senxi-conteudost/main/huds/3%20DEDOS/HUD%203.jpg",
"type": "3 DEDOS"
},
{
"id": "10",
"img": "https://raw.githubusercontent.com/thzzyt/senxi-conteudost/main/huds/4%20DEDOS/HUD%201.jpg",
"type": "4 DEDOS"
},
{
"id": "12",
"img": "https://raw.githubusercontent.com/thzzyt/senxi-conteudost/main/huds/4%20DEDOS/HUD%202.jpg",
"type": "4 DEDOS"
},
{
"id": "13",
"img": "https://raw.githubusercontent.com/thzzyt/senxi-conteudost/main/huds/4%20DEDOS/HUD%203.jpg",
"type": "4 DEDOS"
}
]
